rocketflightsim/__init__.py
rocketflightsim/constants.py
rocketflightsim/flight_simulation.py
rocketflightsim/helper_functions.py
rocketflightsim/rocket_classes.py
rocketflightsim/tools/__init__.py
rocketflightsim/tools/fin_flutter.py
rocketflightsim/tools/max_theoretical_g_v.py
rocketflightsim/tools/plotting_functions.py
rocketflightsim/tools/sensitivity_analyses_comparison.py
rocketflightsim-0.2.0.dist-info/LICENSE
rocketflightsim-0.2.0.dist-info/METADATA
rocketflightsim-0.2.0.dist-info/WHEEL
rocketflightsim-0.2.0.dist-info/top_level.txt
rocketflightsim-0.2.0.dist-info/RECORD
