Metadata-Version: 2.1
Name: rocketflightsim
Version: 0.2.0
Summary: A lightweight rocket flight simulator.
Home-page: https://github.com/werocketry/RocketFlightSim
Author: Giorgio Chassikos, Western Engineering Rocketry Team
Author-email: werocketry@gmail.com
License: MIT
Classifier: Programming Language :: Python :: 3
Classifier: License :: OSI Approved :: MIT License
Classifier: Operating System :: OS Independent
Requires-Python: >=3.6
License-File: LICENSE
Requires-Dist: matplotlib
Requires-Dist: numpy
Requires-Dist: pandas
